access_github.py
access_github-1.1.0.dist-info/METADATA
access_github-1.1.0.dist-info/WHEEL
access_github-1.1.0.dist-info/entry_points.txt
access_github-1.1.0.dist-info/top_level.txt
access_github-1.1.0.dist-info/RECORD
