Metadata-Version: 2.1
Name: access-github
Version: 1.1.0
Requires-Dist: requests
